README.rst
setup.py
uperations/__init__.py
uperations/documentable.py
uperations/kernel.py
uperations/library.py
uperations/operation.py
uperations/operation_observer.py
uperations/exceptions/__init__.py
uperations/exceptions/library.py
uperations_kernel.egg-info/PKG-INFO
uperations_kernel.egg-info/SOURCES.txt
uperations_kernel.egg-info/dependency_links.txt
uperations_kernel.egg-info/top_level.txt