Metadata-Version: 1.0
Name: uperations-kernel
Version: 0.0.10
Summary: UNKNOWN
Home-page: https://github.com/baminou/uperations-kernel
Author: Brice Aminou
Author-email: brice.aminou@gmail.com
License: Creative Commons Attribution-Noncommercial-Share Alike license
Keywords: workflow tool
Platform: UNKNOWN
